{
  "collectionName": "components_blocks_info_blocks",
  "info": {
    "displayName": "infoBlock"
  },
  "options": {},
  "attributes": {
    "reversed": {
      "type": "boolean",
      "default": false
    },
    "image": {
      "type": "media",
      "multiple": false,
      "allowedTypes": [
        "images"
      ]
    },
    "heading": {
      "type": "string"
    },
    "content": {
      "type": "richtext"
    },
    "cta": {
      "type": "component",
      "component": "elements.link",
      "repeatable": false
    },
    "theme": {
      "type": "enumeration",
      "enum": [
        "turquoise",
        "orange"
      ]
    }
  },
  "config": {}
}
